syse/__init__.py
syse/_syse.py
syse-0.1.3.dist-info/LICENSE
syse-0.1.3.dist-info/METADATA
syse-0.1.3.dist-info/WHEEL
syse-0.1.3.dist-info/top_level.txt
syse-0.1.3.dist-info/RECORD
