Metadata-Version: 2.1
Name: syse
Version: 0.1.3
Summary: Systems & Industrial Engineering Python Package
Home-page: https://github.com/Apex-Engineering-Management/SysE
Author: Jonathon Nicholson
Author-email: Jonathon Nicholson <Jonathon@apexpromgt.com>
License: MIT License
Project-URL: Homepage, https://github.com/Apex-Engineering-Management/SysE
Project-URL: Documentation, https://syse.readthedocs.io/en/latest/
Project-URL: Bug Tracker, https://github.com/Apex-Engineering-Management/SysE/issues
Classifier: Programming Language :: Python :: 3
Classifier: License :: OSI Approved :: MIT License
Classifier: Operating System :: OS Independent
Requires-Python: >=3.7
License-File: LICENSE
Requires-Dist: numpy (<=1.23.2)
